Py2Corona/Behaviors.py
Py2Corona/Classes.py
Py2Corona/Consts.py
Py2Corona/__init__.py
Py2Corona/singletons.py
Py2Corona/utils.py
pyforcorona-0.1.2.dist-info/METADATA
pyforcorona-0.1.2.dist-info/RECORD
pyforcorona-0.1.2.dist-info/WHEEL
pyforcorona-0.1.2.dist-info/top_level.txt
